tinybird_cdk/__init__.py
tinybird_cdk/config.py
tinybird_cdk/connector.py
tinybird_cdk/errors.py
tinybird_cdk/export.py
tinybird_cdk/formats.py
tinybird_cdk/logger.py
tinybird_cdk/migration.py
tinybird_cdk/schema.py
tinybird_cdk/tinybird.py
tinybird_cdk/utils.py
tinybird_cdk/cloud/__init__.py
tinybird_cdk/cloud/abstract_client.py
tinybird_cdk/cloud/gcp.py
tinybird_cdk/cloud/gcs.py
tinybird_cdk/cloud/s3.py
tinybird_cdk/connectors/__init__.py
tinybird_cdk/connectors/bigquery.py
tinybird_cdk/connectors/gcs.py
tinybird_cdk/connectors/kinesis.py
tinybird_cdk/connectors/mysql.py
tinybird_cdk/connectors/postgresql.py
tinybird_cdk/connectors/s3.py
tinybird_cdk/connectors/snowflake.py
tinybird_cdk/connectors/sqlite.py
tinybird_cdk-0.17.28.dist-info/METADATA
tinybird_cdk-0.17.28.dist-info/WHEEL
tinybird_cdk-0.17.28.dist-info/top_level.txt
tinybird_cdk-0.17.28.dist-info/RECORD
